procoli/__init__.py
procoli/mp_procoli_functions.py
procoli/mp_to_cobaya_functions.py
procoli/procoli_errors.py
procoli/procoli_io.py
procoli/procoli_plots.py
procoli/data/MP_experiment_crosslist.csv
procoli-1.0.3.dist-info/LICENSE.txt
procoli-1.0.3.dist-info/METADATA
procoli-1.0.3.dist-info/WHEEL
procoli-1.0.3.dist-info/top_level.txt
procoli-1.0.3.dist-info/RECORD
