Metadata-Version: 2.1
Name: procoli
Version: 1.0.3
Summary: A python package that wraps MontePython to provide profile likelihoods for cosmological datasets
Author-email: Tanvi Karwal <karwal@uchicago.edu>, Daniel Pfeffer <dnpfeffe@gmail.com>
License: You are licensed to use this software free of charge within the 
Project-URL: Homepage, https://github.com/tkarwal/procoli
Classifier: Programming Language :: Python :: 3
Classifier: Operating System :: OS Independent
Requires-Python: >=3.7
License-File: LICENSE.txt
Requires-Dist: numpy
Requires-Dist: matplotlib
Requires-Dist: getdist >=1.3.2
Requires-Dist: importlib-resources
